ReactWebpackCookbook/README.md
ReactWebpackCookbook/__init__.py
ReactWebpackCookbook/__main__.py
ReactWebpackCookbook/file.epub
ReactWebpackCookbook/index.html
ReactWebpackCookbook/css/__init__.py
ReactWebpackCookbook/css/annotations.css
ReactWebpackCookbook/css/main.css
ReactWebpackCookbook/css/normalize.css
ReactWebpackCookbook/css/popup.css
ReactWebpackCookbook/font/__init__.py
ReactWebpackCookbook/font/fontello.eot
ReactWebpackCookbook/font/fontello.svg
ReactWebpackCookbook/font/fontello.ttf
ReactWebpackCookbook/font/fontello.woff
ReactWebpackCookbook/img/__init__.py
ReactWebpackCookbook/img/annotator-glyph-sprite.png
ReactWebpackCookbook/img/annotator-icon-sprite.png
ReactWebpackCookbook/img/apple-touch-icon.png
ReactWebpackCookbook/img/cancelfullscreen.png
ReactWebpackCookbook/img/close.png
ReactWebpackCookbook/img/fullscreen.png
ReactWebpackCookbook/img/loader.gif
ReactWebpackCookbook/img/menu-icon.png
ReactWebpackCookbook/img/save.png
ReactWebpackCookbook/img/saved.png
ReactWebpackCookbook/img/settings-s.png
ReactWebpackCookbook/img/settings.png
ReactWebpackCookbook/img/star.png
ReactWebpackCookbook/js/__init__.py
ReactWebpackCookbook/js/epub.js
ReactWebpackCookbook/js/epub.min.js
ReactWebpackCookbook/js/epub.min.map
ReactWebpackCookbook/js/hooks.min.js
ReactWebpackCookbook/js/hooks.min.map
ReactWebpackCookbook/js/reader.js
ReactWebpackCookbook/js/reader.js.map
ReactWebpackCookbook/js/reader.min.js
ReactWebpackCookbook/js/reader.min.map
ReactWebpackCookbook/js/hooks/__init__.py
ReactWebpackCookbook/js/hooks/extensions/__init__.py
ReactWebpackCookbook/js/hooks/extensions/highlight.js
ReactWebpackCookbook/js/libs/__init__.py
ReactWebpackCookbook/js/libs/jquery.min.js
ReactWebpackCookbook/js/libs/localforage.min.js
ReactWebpackCookbook/js/libs/screenfull.js
ReactWebpackCookbook/js/libs/screenfull.min.js
ReactWebpackCookbook/js/libs/zip.min.js
ReactWebpackCookbook/js/plugins/__init__.py
ReactWebpackCookbook/js/plugins/hypothesis.js
react_webpack_cookbook-2024.3.1.0.dist-info/METADATA
react_webpack_cookbook-2024.3.1.0.dist-info/WHEEL
react_webpack_cookbook-2024.3.1.0.dist-info/entry_points.txt
react_webpack_cookbook-2024.3.1.0.dist-info/top_level.txt
react_webpack_cookbook-2024.3.1.0.dist-info/RECORD
